fastapi_rest_utils/__init__.py
fastapi_rest_utils/deps.py
fastapi_rest_utils/errors.py
fastapi_rest_utils/protocols.py
fastapi_rest_utils/router.py
fastapi_rest_utils/viewsets/__init__.py
fastapi_rest_utils/viewsets/base.py
fastapi_rest_utils/viewsets/sqlalchemy.py
fastapi_rest_utils-0.1.4.dist-info/licenses/LICENSE
fastapi_rest_utils-0.1.4.dist-info/METADATA
fastapi_rest_utils-0.1.4.dist-info/WHEEL
fastapi_rest_utils-0.1.4.dist-info/top_level.txt
fastapi_rest_utils-0.1.4.dist-info/RECORD
