Metadata-Version: 2.4
Name: fastapi-rest-utils
Version: 0.1.4
Summary: Utilities for building REST APIs with FastAPI
Author-email: Babaian Daniel <babaian.daniel@icloud.com>
License-Expression: MIT
Project-URL: Homepage, https://github.com/Mdanic75/fastapi_rest_utils
Project-URL: Repository, https://github.com/Mdanic75/fastapi_rest_utils
Project-URL: Issues, https://github.com/Mdanic75/fastapi_rest_utils/issues
Classifier: Development Status :: 3 - Alpha
Classifier: Intended Audience :: Developers
Classifier: Programming Language :: Python :: 3
Classifier: Programming Language :: Python :: 3.8
Classifier: Programming Language :: Python :: 3.9
Classifier: Programming Language :: Python :: 3.10
Classifier: Programming Language :: Python :: 3.11
Classifier: Programming Language :: Python :: 3.12
Requires-Python: >=3.8
License-File: LICENSE
Requires-Dist: fastapi>=0.100.0
Requires-Dist: pydantic>=2.0.0
Requires-Dist: sqlalchemy>=2.0.0
Requires-Dist: typing-extensions>=4.0.0
Provides-Extra: dev
Requires-Dist: pytest>=7.0.0; extra == "dev"
Requires-Dist: pytest-asyncio>=0.21.0; extra == "dev"
Requires-Dist: black>=23.0.0; extra == "dev"
Requires-Dist: isort>=5.12.0; extra == "dev"
Requires-Dist: mypy>=1.0.0; extra == "dev"
Requires-Dist: autopep8>=2.0.0; extra == "dev"
Dynamic: license-file
